lib/__init__.py
lib/EDALIB/__init__.py
lib/EDALIB/core.py
lib/agents/__init__.py
lib/agents/agent.py
lib/ml/__init__.py
lib/ml/base.py
lib/ml/imputer.py
lib/ml/preprocessing.py
lib/ml/Trainer/__init__.py
lib/ml/Trainer/evaluate_models_fun.py
lib/ml/chain/__init__.py
lib/ml/chain/compose.py
lib/ml/chain/pipeline.py
visualizerlib-0.2.3.dist-info/licenses/LICENSE
visualizerlib-0.2.3.dist-info/METADATA
visualizerlib-0.2.3.dist-info/WHEEL
visualizerlib-0.2.3.dist-info/top_level.txt
visualizerlib-0.2.3.dist-info/RECORD
