Metadata-Version: 2.4
Name: visualizerlib
Version: 0.2.3
Summary: A simple visualization and EDA helper package. Includes: Agent execution for plot insights, ML helper classes and functions, Preprocessor, imputer, column transformer, and chaining pipeline
Home-page: https://github.com/Vishnuu011/visualizerlib
Author: Vishnu
Author-email: Vishnu <vishnurrajeev@gmail.com>
License: MIT
Requires-Python: >=3.7
License-File: LICENSE
Requires-Dist: pandas
Requires-Dist: numpy
Requires-Dist: matplotlib
Requires-Dist: seaborn
Requires-Dist: groq
Requires-Dist: langchain
Requires-Dist: pydantic
Requires-Dist: langchain-core
Requires-Dist: ipython
Requires-Dist: scikit-learn
Requires-Dist: tqdm
Dynamic: author
Dynamic: home-page
Dynamic: license-file
Dynamic: requires-python
